zymoKrisIndex/__init__.py
zymoKrisIndex/amino1000.json
zymoKrisIndex/dna1000.json
zymoKrisIndex/krisIndex.py
zymoKrisIndex/requirements.txt
zymoKrisIndex/rna1000.json
zymokrisindex-0.0.3.dist-info/METADATA
zymokrisindex-0.0.3.dist-info/WHEEL
zymokrisindex-0.0.3.dist-info/licenses/LICENSE
zymokrisindex-0.0.3.dist-info/RECORD
