Metadata-Version: 2.4
Name: zymoKrisIndex
Version: 0.0.3
Summary: A package for calculating kmer complexity of sequences using Burrows-Wheeler compressibility.
Project-URL: Homepage, https://github.com/Zymo-Research/krisIndex
Project-URL: Bug Tracker, https://github.com/Zymo-Research/krisIndex/issues
Author-email: Michael Weinstein <mweinstein@zymoresearch.com>
License:                     GNU AFFERO GENERAL PUBLIC LICENSE
License-File: LICENSE
Classifier: Operating System :: OS Independent
Classifier: Programming Language :: Python :: 3
Requires-Python: >=3.10
Requires-Dist: mpire>=2.0
Requires-Dist: pydantic>=2.0
